{
   "agent": "Tarantool websocket",
   "behavior": "OK",
   "behaviorClose": "OK",
   "case": 54,
   "closedByMe": false,
   "createStats": true,
   "createWirelog": true,
   "description": "Send unfragmented Text Message after Continuation Frame with FIN = true, where there is nothing to continue, sent in per-frame chops.",
   "droppedByMe": false,
   "duration": 2,
   "expectation": "The connection is failed immediately, since there is no message to continue.",
   "expected": {
      "OK": []
   },
   "expectedClose": {
      "closeCode": [
         1002
      ],
      "closedByMe": false,
      "requireClean": false
   },
   "failedByMe": false,
   "httpRequest": "GET / HTTP/1.1\r\nUser-Agent: AutobahnTestSuite/0.8.0-0.10.9\r\nHost: 127.0.0.1:8443\r\nUpgrade: WebSocket\r\nConnection: Upgrade\r\nPragma: no-cache\r\nCache-Control: no-cache\r\nSec-WebSocket-Key: +b9iiN8ToscwY7YxN/UBYA==\r\nSec-WebSocket-Version: 13\r\n\r\n",
   "httpResponse": "HTTP/1.1 101 Switching Protocols\r\nSec-WebSocket-Accept: S5cyUUn2Dxf5mufh5G1nVAqyIkk=\r\nUpgrade: websocket\r\nConnection: Upgrade\r\n\r\n",
   "id": "5.10",
   "isServer": false,
   "localCloseCode": 1000,
   "localCloseReason": null,
   "received": [],
   "remoteCloseCode": 1002,
   "remoteCloseReason": "continuation frame without head frame",
   "reportCompressionRatio": false,
   "reportTime": false,
   "result": "Actual events match at least one expected.",
   "resultClose": "Connection was properly closed",
   "rxFrameStats": {
      "8": 1,
      "9": 1
   },
   "rxOctetStats": {
      "2": 1,
      "41": 1,
      "129": 1
   },
   "started": "2018-08-28T11:51:20.732Z",
   "trafficStats": null,
   "txFrameStats": {
      "0": 1,
      "1": 1,
      "8": 1,
      "10": 1
   },
   "txOctetStats": {
      "6": 1,
      "8": 1,
      "19": 1,
      "30": 1,
      "240": 1
   },
   "wasClean": true,
   "wasCloseHandshakeTimeout": false,
   "wasNotCleanReason": null,
   "wasOpenHandshakeTimeout": false,
   "wasServerConnectionDropTimeout": false,
   "wirelog": [
      [
         "TO",
         [
            240,
            "474554202f20485454502f312e310d0a557365722d4167656e743a204175746f6261686e5465737453756974652f302e382e302d302e31302e390d0a486f7374 ..."
         ],
         false
      ],
      [
         "RO",
         [
            129,
            "485454502f312e312031303120537769746368696e672050726f746f636f6c730d0a5365632d576562536f636b65742d4163636570743a205335637955556e32 ..."
         ]
      ],
      [
         "TF",
         [
            24,
            "non-continuation payload"
         ],
         0,
         true,
         0,
         "a84767a2",
         null,
         null,
         true
      ],
      [
         "TO",
         [
            30,
            "8098a84767a2c628098fcb2809d6c12912c3dc2e08cc883706dbc42806c6"
         ],
         true
      ],
      [
         "TF",
         [
            13,
            "Hello, world!"
         ],
         1,
         true,
         0,
         "9c9f0e90",
         null,
         null,
         true
      ],
      [
         "KL",
         1
      ],
      [
         "RO",
         [
            2,
            "8900"
         ]
      ],
      [
         "RF",
         [
            0,
            ""
         ],
         9,
         true,
         0,
         false,
         null
      ],
      [
         "TF",
         [
            0,
            ""
         ],
         10,
         true,
         0,
         "5cd522c2",
         null,
         null,
         false
      ],
      [
         "TO",
         [
            19,
            "818d9c9f0e90d4fa62fcf3b32ee7f3ed62f4bd"
         ],
         true
      ],
      [
         "TO",
         [
            6,
            "8a805cd522c2"
         ],
         false
      ],
      [
         "RO",
         [
            41,
            "882703ea636f6e74696e756174696f6e206672616d6520776974686f75742068656164206672616d65"
         ]
      ],
      [
         "RF",
         [
            39,
            "0x03ea636f6e74696e756174696f6e206672616d6520776974686f75742068656164206672616d65"
         ],
         8,
         true,
         0,
         false,
         null
      ],
      [
         "TF",
         [
            2,
            "0x03e8"
         ],
         8,
         true,
         0,
         "083c0705",
         null,
         null,
         false
      ],
      [
         "TO",
         [
            8,
            "8882083c07050bd4"
         ],
         false
      ]
   ]
}