{
   "agent": "Tarantool websocket",
   "behavior": "OK",
   "behaviorClose": "OK",
   "case": 261,
   "closedByMe": true,
   "createStats": true,
   "createWirelog": true,
   "description": "Send fragmented text message message with message payload of length 4 * 2**20 (4M). Sent out in fragments of 64.",
   "droppedByMe": false,
   "duration": 2854,
   "expectation": "Receive echo'ed text message (with payload as sent).",
   "expected": {},
   "expectedClose": {
      "closeCode": [
         1000
      ],
      "closedByMe": true,
      "requireClean": true
   },
   "failedByMe": false,
   "httpRequest": "GET / HTTP/1.1\r\nUser-Agent: AutobahnTestSuite/0.8.0-0.10.9\r\nHost: 127.0.0.1:8080\r\nUpgrade: WebSocket\r\nConnection: Upgrade\r\nPragma: no-cache\r\nCache-Control: no-cache\r\nSec-WebSocket-Key: 7o9K3HWJYu6SJrSVQwC3NQ==\r\nSec-WebSocket-Version: 13\r\n\r\n",
   "httpResponse": "HTTP/1.1 101 Switching Protocols\r\nSec-WebSocket-Accept: HsMfOQTCBhz3VQ7mGgDRauwRkOQ=\r\nUpgrade: websocket\r\nConnection: Upgrade\r\n\r\n",
   "id": "9.3.1",
   "isServer": false,
   "localCloseCode": 1000,
   "localCloseReason": null,
   "received": [],
   "remoteCloseCode": null,
   "remoteCloseReason": null,
   "reportCompressionRatio": false,
   "reportTime": true,
   "result": "Received text message of length 4194304.",
   "resultClose": "Connection was properly closed",
   "rxFrameStats": {
      "0": 65536,
      "1": 1,
      "8": 1
   },
   "rxOctetStats": {
      "2": 1,
      "66": 936,
      "129": 1,
      "132": 4446,
      "198": 1447,
      "264": 894,
      "330": 584,
      "396": 661,
      "462": 440,
      "528": 407,
      "594": 235,
      "660": 288,
      "726": 131,
      "792": 150,
      "858": 88,
      "924": 130,
      "926": 1,
      "990": 72,
      "1056": 82,
      "1122": 51,
      "1188": 78,
      "1254": 43,
      "1320": 56,
      "1386": 43,
      "1452": 53,
      "1518": 34,
      "1584": 30,
      "1650": 36,
      "1716": 32,
      "1782": 19,
      "1848": 26,
      "1914": 10,
      "1980": 23,
      "2046": 11,
      "2112": 12,
      "2178": 11,
      "2244": 12,
      "2310": 9,
      "2376": 8,
      "2442": 6,
      "2508": 9,
      "2574": 3,
      "2640": 6,
      "2706": 7,
      "2772": 4,
      "2838": 2,
      "2904": 4,
      "2970": 7,
      "3036": 4,
      "3102": 2,
      "3168": 4,
      "3300": 3,
      "3366": 2,
      "3432": 1,
      "3498": 2,
      "3960": 1,
      "4158": 2,
      "4224": 1,
      "4356": 1,
      "4488": 2,
      "4620": 1,
      "4752": 2,
      "4884": 2,
      "4950": 1,
      "5016": 1,
      "5280": 1,
      "5676": 2,
      "5808": 1,
      "5940": 1,
      "6072": 1,
      "6204": 1,
      "6336": 1,
      "6468": 1,
      "6600": 1,
      "6864": 1,
      "6996": 1,
      "7392": 2,
      "7986": 1,
      "8052": 1,
      "8316": 1,
      "8448": 1,
      "9042": 1,
      "10758": 1,
      "11088": 1,
      "11748": 2,
      "12144": 1,
      "14322": 1,
      "17688": 1
   },
   "started": "2018-07-25T19:46:14.047Z",
   "trafficStats": null,
   "txFrameStats": {
      "0": 65536,
      "1": 1,
      "8": 1
   },
   "txOctetStats": {
      "6": 1,
      "8": 1,
      "70": 65536,
      "240": 1
   },
   "wasClean": true,
   "wasCloseHandshakeTimeout": false,
   "wasNotCleanReason": null,
   "wasOpenHandshakeTimeout": false,
   "wasServerConnectionDropTimeout": false,
   "wirelog": [
      [
         "TO",
         [
            240,
            "474554202f20485454502f312e310d0a557365722d4167656e743a204175746f6261686e5465737453756974652f302e382e302d302e31302e390d0a486f7374 ..."
         ],
         false
      ],
      [
         "RO",
         [
            129,
            "485454502f312e312031303120537769746368696e672050726f746f636f6c730d0a5365632d576562536f636b65742d4163636570743a2048734d664f515443 ..."
         ]
      ],
      [
         "TI",
         100
      ],
      [
         "TF",
         [
            2,
            "0x03e8"
         ],
         8,
         true,
         0,
         "a3f7e12e",
         null,
         null,
         false
      ],
      [
         "TO",
         [
            8,
            "8882a3f7e12ea01f"
         ],
         false
      ],
      [
         "RO",
         [
            2,
            "8800"
         ]
      ],
      [
         "RF",
         [
            0,
            ""
         ],
         8,
         true,
         0,
         false,
         null
      ]
   ]
}